brainiac_client/__init__.py
brainiac_client/_version.py
brainiac_client/client.py
brainiac_client/constants.py
brainiac_client/errors.py
brainiac_client/scientist.py
brainiac_client/protos/__init__.py
brainiac_client/protos/brainiac_pb2.py
brainiac_client/protos/brainiac_pb2_grpc.py
brainiac_client/tests/__init__.py
brainiac_client/tests/third_party.py
brainiac_client-0.0.1.7rc0.dist-info/AUTHORS.rst
brainiac_client-0.0.1.7rc0.dist-info/LICENSE
brainiac_client-0.0.1.7rc0.dist-info/METADATA
brainiac_client-0.0.1.7rc0.dist-info/WHEEL
brainiac_client-0.0.1.7rc0.dist-info/top_level.txt
brainiac_client-0.0.1.7rc0.dist-info/RECORD
